[
  {
    "userCode": "1300217",
    "action": "menu_click",
    "menu": "통합인수가이드",
    "timestamp": "2025-10-14T23:17:06.407Z",
    "date": "2025-10-15"
  },
  {
    "userCode": "1300217",
    "action": "menu_click",
    "menu": "통합인수가이드",
    "timestamp": "2025-10-14T23:18:31.872Z",
    "date": "2025-10-15"
  },
  {
    "userCode": "1300217",
    "action": "menu_click",
    "menu": "통합인수가이드",
    "timestamp": "2025-10-14T23:18:48.946Z",
    "date": "2025-10-15"
  },
  {
    "userCode": "1300217",
    "action": "menu_click",
    "menu": "통합인수가이드",
    "timestamp": "2025-10-14T23:19:32.560Z",
    "date": "2025-10-15"
  },
  {
    "userCode": "1300217",
    "action": "menu_click",
    "menu": "통합인수가이드",
    "timestamp": "2025-10-14T23:24:20.663Z",
    "date": "2025-10-15"
  },
  {
    "userCode": "1300195",
    "action": "menu_click",
    "menu": "통합인수가이드",
    "timestamp": "2025-10-14T23:45:51.218Z",
    "date": "2025-10-15"
  },
  {
    "userCode": "1300217",
    "action": "menu_click",
    "menu": "통합인수가이드",
    "timestamp": "2025-10-14T23:47:08.009Z",
    "date": "2025-10-15"
  },
  {
    "userCode": "1300217",
    "action": "menu_click",
    "menu": "통합인수가이드",
    "timestamp": "2025-10-15T00:08:18.746Z",
    "date": "2025-10-15"
  },
  {
    "userCode": "1301644",
    "action": "login",
    "menu": "일반로그인",
    "timestamp": "2025-10-15T00:21:17.260Z",
    "date": "2025-10-15"
  },
  {
    "userCode": "1300165",
    "action": "menu_click",
    "menu": "보장분석만들기",
    "timestamp": "2025-10-15T00:21:21.286Z",
    "date": "2025-10-15"
  },
  {
    "userCode": "1300165",
    "action": "menu_click",
    "menu": "보장분석만들기",
    "timestamp": "2025-10-15T00:21:26.245Z",
    "date": "2025-10-15"
  },
  {
    "userCode": "1300165",
    "action": "menu_click",
    "menu": "보장분석만들기",
    "timestamp": "2025-10-15T00:21:29.520Z",
    "date": "2025-10-15"
  },
  {
    "userCode": "1300165",
    "action": "menu_click",
    "menu": "보장분석만들기",
    "timestamp": "2025-10-15T00:21:32.177Z",
    "date": "2025-10-15"
  },
  {
    "userCode": "1300165",
    "action": "menu_click",
    "menu": "보장분석만들기",
    "timestamp": "2025-10-15T00:21:33.109Z",
    "date": "2025-10-15"
  },
  {
    "userCode": "1300165",
    "action": "menu_click",
    "menu": "보장분석만들기",
    "timestamp": "2025-10-15T00:21:34.895Z",
    "date": "2025-10-15"
  },
  {
    "userCode": "1300165",
    "action": "menu_click",
    "menu": "보장분석만들기",
    "timestamp": "2025-10-15T00:21:37.874Z",
    "date": "2025-10-15"
  },
  {
    "userCode": "1300165",
    "action": "menu_click",
    "menu": "보장분석만들기",
    "timestamp": "2025-10-15T00:21:40.648Z",
    "date": "2025-10-15"
  },
  {
    "userCode": "1300210",
    "action": "menu_click",
    "menu": "통합인수가이드",
    "timestamp": "2025-10-15T00:21:42.339Z",
    "date": "2025-10-15"
  },
  {
    "userCode": "1300165",
    "action": "menu_click",
    "menu": "보장분석만들기",
    "timestamp": "2025-10-15T00:21:42.461Z",
    "date": "2025-10-15"
  },
  {
    "userCode": "1300165",
    "action": "menu_click",
    "menu": "보장분석만들기",
    "timestamp": "2025-10-15T00:21:46.265Z",
    "date": "2025-10-15"
  },
  {
    "userCode": "1300165",
    "action": "menu_click",
    "menu": "보장분석만들기",
    "timestamp": "2025-10-15T00:21:45.162Z",
    "date": "2025-10-15"
  },
  {
    "userCode": "1300156",
    "action": "login",
    "menu": "일반로그인",
    "timestamp": "2025-10-15T00:22:01.275Z",
    "date": "2025-10-15"
  },
  {
    "userCode": "1300165",
    "action": "menu_click",
    "menu": "보장분석만들기",
    "timestamp": "2025-10-15T00:22:04.344Z",
    "date": "2025-10-15"
  },
  {
    "userCode": "1300165",
    "action": "menu_click",
    "menu": "보장분석만들기",
    "timestamp": "2025-10-15T00:22:22.103Z",
    "date": "2025-10-15"
  },
  {
    "userCode": "1300165",
    "action": "menu_click",
    "menu": "보장분석만들기",
    "timestamp": "2025-10-15T00:22:23.562Z",
    "date": "2025-10-15"
  },
  {
    "userCode": "1300165",
    "action": "menu_click",
    "menu": "보장분석만들기",
    "timestamp": "2025-10-15T00:22:41.691Z",
    "date": "2025-10-15"
  },
  {
    "userCode": "1301644",
    "action": "menu_click",
    "menu": "통합인수가이드",
    "timestamp": "2025-10-15T00:22:46.457Z",
    "date": "2025-10-15"
  },
  {
    "userCode": "1300165",
    "action": "menu_click",
    "menu": "보장분석만들기",
    "timestamp": "2025-10-15T00:22:51.141Z",
    "date": "2025-10-15"
  },
  {
    "userCode": "1300165",
    "action": "login",
    "menu": "일반로그인",
    "timestamp": "2025-10-15T00:23:06.012Z",
    "date": "2025-10-15"
  },
  {
    "userCode": "1300165",
    "action": "menu_click",
    "menu": "보장분석만들기",
    "timestamp": "2025-10-15T00:23:15.469Z",
    "date": "2025-10-15"
  },
  {
    "userCode": "1300165",
    "action": "menu_click",
    "menu": "보장분석만들기",
    "timestamp": "2025-10-15T00:23:20.765Z",
    "date": "2025-10-15"
  },
  {
    "userCode": "1300165",
    "action": "menu_click",
    "menu": "보장분석만들기",
    "timestamp": "2025-10-15T00:23:44.568Z",
    "date": "2025-10-15"
  },
  {
    "userCode": "1300165",
    "action": "menu_click",
    "menu": "보장분석만들기",
    "timestamp": "2025-10-15T00:23:50.719Z",
    "date": "2025-10-15"
  },
  {
    "userCode": "1300165",
    "action": "menu_click",
    "menu": "보장분석만들기",
    "timestamp": "2025-10-15T00:24:02.458Z",
    "date": "2025-10-15"
  },
  {
    "userCode": "1300156",
    "action": "menu_click",
    "menu": "보장분석만들기",
    "timestamp": "2025-10-15T00:24:09.141Z",
    "date": "2025-10-15"
  },
  {
    "userCode": "1300165",
    "action": "menu_click",
    "menu": "보장분석만들기",
    "timestamp": "2025-10-15T00:24:13.103Z",
    "date": "2025-10-15"
  },
  {
    "userCode": "1300165",
    "action": "login",
    "menu": "일반로그인",
    "timestamp": "2025-10-15T00:24:41.810Z",
    "date": "2025-10-15"
  },
  {
    "userCode": "1300165",
    "action": "menu_click",
    "menu": "보장분석만들기",
    "timestamp": "2025-10-15T00:24:43.014Z",
    "date": "2025-10-15"
  },
  {
    "userCode": "1300165",
    "action": "menu_click",
    "menu": "보장분석만들기",
    "timestamp": "2025-10-15T00:25:53.610Z",
    "date": "2025-10-15"
  },
  {
    "userCode": "1300165",
    "action": "menu_click",
    "menu": "보장분석만들기",
    "timestamp": "2025-10-15T00:26:10.512Z",
    "date": "2025-10-15"
  },
  {
    "userCode": "1300165",
    "action": "menu_click",
    "menu": "보장분석만들기",
    "timestamp": "2025-10-15T00:31:16.012Z",
    "date": "2025-10-15"
  },
  {
    "userCode": "1300165",
    "action": "menu_click",
    "menu": "보장분석만들기",
    "timestamp": "2025-10-15T00:31:43.269Z",
    "date": "2025-10-15"
  },
  {
    "userCode": "1300165",
    "action": "menu_click",
    "menu": "보장분석만들기",
    "timestamp": "2025-10-15T00:32:00.792Z",
    "date": "2025-10-15"
  },
  {
    "userCode": "1300165",
    "action": "menu_click",
    "menu": "보장분석만들기",
    "timestamp": "2025-10-15T00:32:43.525Z",
    "date": "2025-10-15"
  },
  {
    "userCode": "1300165",
    "action": "menu_click",
    "menu": "보장분석만들기",
    "timestamp": "2025-10-15T00:32:57.221Z",
    "date": "2025-10-15"
  },
  {
    "userCode": "1300165",
    "action": "menu_click",
    "menu": "보장분석만들기",
    "timestamp": "2025-10-15T00:33:14.526Z",
    "date": "2025-10-15"
  },
  {
    "userCode": "1300165",
    "action": "menu_click",
    "menu": "보장분석만들기",
    "timestamp": "2025-10-15T00:34:06.542Z",
    "date": "2025-10-15"
  },
  {
    "userCode": "1300165",
    "action": "menu_click",
    "menu": "보장분석만들기",
    "timestamp": "2025-10-15T00:34:29.004Z",
    "date": "2025-10-15"
  },
  {
    "userCode": "1300165",
    "action": "menu_click",
    "menu": "보장분석만들기",
    "timestamp": "2025-10-15T00:34:49.773Z",
    "date": "2025-10-15"
  },
  {
    "userCode": "1300165",
    "action": "menu_click",
    "menu": "보장분석만들기",
    "timestamp": "2025-10-15T00:35:19.385Z",
    "date": "2025-10-15"
  },
  {
    "userCode": "1300165",
    "action": "menu_click",
    "menu": "보장분석만들기",
    "timestamp": "2025-10-15T00:35:27.192Z",
    "date": "2025-10-15"
  },
  {
    "userCode": "1300165",
    "action": "menu_click",
    "menu": "보장분석만들기",
    "timestamp": "2025-10-15T00:35:41.835Z",
    "date": "2025-10-15"
  },
  {
    "userCode": "1300165",
    "action": "menu_click",
    "menu": "보장분석만들기",
    "timestamp": "2025-10-15T00:35:46.469Z",
    "date": "2025-10-15"
  },
  {
    "userCode": "1300165",
    "action": "menu_click",
    "menu": "보장분석만들기",
    "timestamp": "2025-10-15T00:36:14.318Z",
    "date": "2025-10-15"
  },
  {
    "userCode": "1300165",
    "action": "menu_click",
    "menu": "보장분석만들기",
    "timestamp": "2025-10-15T00:36:38.005Z",
    "date": "2025-10-15"
  },
  {
    "userCode": "1300165",
    "action": "menu_click",
    "menu": "보장분석만들기",
    "timestamp": "2025-10-15T00:37:14.169Z",
    "date": "2025-10-15"
  },
  {
    "userCode": "1300165",
    "action": "menu_click",
    "menu": "보장분석만들기",
    "timestamp": "2025-10-15T00:37:19.841Z",
    "date": "2025-10-15"
  },
  {
    "userCode": "1300165",
    "action": "menu_click",
    "menu": "보장분석만들기",
    "timestamp": "2025-10-15T00:37:19.799Z",
    "date": "2025-10-15"
  },
  {
    "userCode": "1300165",
    "action": "login",
    "menu": "일반로그인",
    "timestamp": "2025-10-15T00:38:01.203Z",
    "date": "2025-10-15"
  },
  {
    "userCode": "1300165",
    "action": "menu_click",
    "menu": "보장분석만들기",
    "timestamp": "2025-10-15T00:38:04.979Z",
    "date": "2025-10-15"
  },
  {
    "userCode": "1300165",
    "action": "menu_click",
    "menu": "보장분석만들기",
    "timestamp": "2025-10-15T00:38:46.321Z",
    "date": "2025-10-15"
  },
  {
    "userCode": "1300165",
    "action": "menu_click",
    "menu": "보장분석만들기",
    "timestamp": "2025-10-15T00:39:22.724Z",
    "date": "2025-10-15"
  },
  {
    "userCode": "1300165",
    "action": "menu_click",
    "menu": "보장분석만들기",
    "timestamp": "2025-10-15T00:40:46.588Z",
    "date": "2025-10-15"
  },
  {
    "userCode": "8091768",
    "action": "menu_click",
    "menu": "통합인수가이드",
    "timestamp": "2025-10-15T00:41:19.938Z",
    "date": "2025-10-15"
  },
  {
    "userCode": "1300165",
    "action": "menu_click",
    "menu": "보장분석만들기",
    "timestamp": "2025-10-15T00:41:46.708Z",
    "date": "2025-10-15"
  }
]