[
  {
    "userCode": "1301046",
    "action": "login",
    "menu": "일반로그인",
    "timestamp": "2025-10-21T20:04:02.991Z",
    "date": "2025-10-22"
  },
  {
    "userCode": "1301046",
    "action": "menu_click",
    "menu": "통합인수가이드",
    "timestamp": "2025-10-21T20:04:09.750Z",
    "date": "2025-10-22"
  },
  {
    "userCode": "1301489",
    "action": "login",
    "menu": "일반로그인",
    "timestamp": "2025-10-21T20:48:11.282Z",
    "date": "2025-10-22"
  },
  {
    "userCode": "1301489",
    "action": "menu_click",
    "menu": "보장분석만들기",
    "timestamp": "2025-10-21T20:48:24.443Z",
    "date": "2025-10-22"
  },
  {
    "userCode": "1301489",
    "action": "menu_click",
    "menu": "인수한도조회",
    "timestamp": "2025-10-21T20:48:42.371Z",
    "date": "2025-10-22"
  },
  {
    "userCode": "1301046",
    "action": "menu_click",
    "menu": "보장분석만들기",
    "timestamp": "2025-10-21T21:03:07.505Z",
    "date": "2025-10-22"
  },
  {
    "userCode": "1301046",
    "action": "menu_click",
    "menu": "연락처조회",
    "timestamp": "2025-10-21T21:03:13.311Z",
    "date": "2025-10-22"
  },
  {
    "userCode": "1301046",
    "action": "menu_click",
    "menu": "인수한도조회",
    "timestamp": "2025-10-21T21:03:29.718Z",
    "date": "2025-10-22"
  }
]