[
  {
    "userCode": "1300110",
    "action": "menu_click",
    "menu": "통합인수가이드",
    "timestamp": "2026-01-07T15:26:48.960Z",
    "date": "2026-01-08"
  },
  {
    "userCode": "1300110",
    "action": "menu_click",
    "menu": "수술비검색",
    "timestamp": "2026-01-07T15:27:05.785Z",
    "date": "2026-01-08"
  },
  {
    "userCode": "1300110",
    "action": "search",
    "menu": "수술비검색:용종",
    "timestamp": "2026-01-07T15:27:11.594Z",
    "date": "2026-01-08"
  },
  {
    "userCode": "1300110",
    "action": "menu_click",
    "menu": "통합인수가이드",
    "timestamp": "2026-01-07T15:27:16.884Z",
    "date": "2026-01-08"
  },
  {
    "userCode": "1300190",
    "action": "menu_click",
    "menu": "통합인수가이드",
    "timestamp": "2026-01-07T21:50:25.807Z",
    "date": "2026-01-08"
  },
  {
    "userCode": "1300217",
    "action": "menu_click",
    "menu": "통합인수가이드",
    "timestamp": "2026-01-07T23:55:49.953Z",
    "date": "2026-01-08"
  },
  {
    "userCode": "1300217",
    "action": "menu_click",
    "menu": "수술비검색",
    "timestamp": "2026-01-08T00:04:44.478Z",
    "date": "2026-01-08"
  },
  {
    "userCode": "1300217",
    "action": "search",
    "menu": "수술비검색:요로결석",
    "timestamp": "2026-01-08T00:04:51.768Z",
    "date": "2026-01-08"
  },
  {
    "userCode": "1300217",
    "action": "search",
    "menu": "수술비검색:체외충격",
    "timestamp": "2026-01-08T00:05:03.538Z",
    "date": "2026-01-08"
  },
  {
    "userCode": "1301422",
    "action": "menu_click",
    "menu": "수술비검색",
    "timestamp": "2026-01-08T00:06:55.564Z",
    "date": "2026-01-08"
  },
  {
    "userCode": "1301422",
    "action": "search",
    "menu": "수술비검색:I83.9",
    "timestamp": "2026-01-08T00:07:07.152Z",
    "date": "2026-01-08"
  },
  {
    "userCode": "1301422",
    "action": "search",
    "menu": "수술비검색:I83",
    "timestamp": "2026-01-08T00:07:32.106Z",
    "date": "2026-01-08"
  },
  {
    "userCode": "1301549",
    "action": "menu_click",
    "menu": "통합인수가이드",
    "timestamp": "2026-01-08T00:11:37.468Z",
    "date": "2026-01-08"
  },
  {
    "userCode": "1300156",
    "action": "login",
    "menu": "일반로그인",
    "timestamp": "2026-01-08T00:13:04.312Z",
    "date": "2026-01-08"
  },
  {
    "userCode": "1300156",
    "action": "menu_click",
    "menu": "수술비검색",
    "timestamp": "2026-01-08T00:13:07.954Z",
    "date": "2026-01-08"
  },
  {
    "userCode": "1300156",
    "action": "search",
    "menu": "수술비검색:대장용종",
    "timestamp": "2026-01-08T00:13:14.613Z",
    "date": "2026-01-08"
  },
  {
    "userCode": "1301309",
    "action": "menu_click",
    "menu": "통합인수가이드",
    "timestamp": "2026-01-08T00:21:40.767Z",
    "date": "2026-01-08"
  },
  {
    "userCode": "1300190",
    "action": "menu_click",
    "menu": "통합인수가이드",
    "timestamp": "2026-01-08T00:44:23.313Z",
    "date": "2026-01-08"
  },
  {
    "userCode": "1301489",
    "action": "menu_click",
    "menu": "수술비검색",
    "timestamp": "2026-01-08T01:12:06.284Z",
    "date": "2026-01-08"
  },
  {
    "userCode": "1301489",
    "action": "search",
    "menu": "수술비검색:대장용좉",
    "timestamp": "2026-01-08T01:12:11.624Z",
    "date": "2026-01-08"
  },
  {
    "userCode": "1301489",
    "action": "search",
    "menu": "수술비검색:대장용종",
    "timestamp": "2026-01-08T01:12:15.629Z",
    "date": "2026-01-08"
  },
  {
    "userCode": "1300217",
    "action": "menu_click",
    "menu": "수술비검색",
    "timestamp": "2026-01-08T01:14:07.152Z",
    "date": "2026-01-08"
  },
  {
    "userCode": "1300217",
    "action": "search",
    "menu": "수술비검색:핀제거",
    "timestamp": "2026-01-08T01:14:13.012Z",
    "date": "2026-01-08"
  }
]