[
  {
    "userCode": "1300190",
    "action": "login",
    "menu": "일반로그인",
    "timestamp": "2026-01-28T22:16:54.072Z",
    "date": "2026-01-29"
  },
  {
    "userCode": "1300190",
    "action": "menu_click",
    "menu": "통합인수가이드",
    "timestamp": "2026-01-28T22:16:55.004Z",
    "date": "2026-01-29"
  },
  {
    "userCode": "1303024",
    "action": "menu_click",
    "menu": "통합인수가이드",
    "timestamp": "2026-01-29T00:01:41.352Z",
    "date": "2026-01-29"
  },
  {
    "userCode": "1300149",
    "action": "menu_click",
    "menu": "연락처조회",
    "timestamp": "2026-01-29T00:02:01.413Z",
    "date": "2026-01-29"
  },
  {
    "userCode": "1300091",
    "action": "menu_click",
    "menu": "통합인수가이드",
    "timestamp": "2026-01-29T00:34:04.201Z",
    "date": "2026-01-29"
  },
  {
    "userCode": "1300091",
    "action": "menu_click",
    "menu": "통합인수가이드",
    "timestamp": "2026-01-29T00:35:04.141Z",
    "date": "2026-01-29"
  },
  {
    "userCode": "1300210",
    "action": "menu_click",
    "menu": "통합인수가이드",
    "timestamp": "2026-01-29T00:40:26.437Z",
    "date": "2026-01-29"
  },
  {
    "userCode": "8091768",
    "action": "menu_click",
    "menu": "통합인수가이드",
    "timestamp": "2026-01-29T00:45:04.725Z",
    "date": "2026-01-29"
  },
  {
    "userCode": "8091768",
    "action": "menu_click",
    "menu": "통합인수가이드",
    "timestamp": "2026-01-29T00:49:46.636Z",
    "date": "2026-01-29"
  },
  {
    "userCode": "8091768",
    "action": "menu_click",
    "menu": "통합인수가이드",
    "timestamp": "2026-01-29T00:52:15.710Z",
    "date": "2026-01-29"
  },
  {
    "userCode": "1300217",
    "action": "menu_click",
    "menu": "통합인수가이드",
    "timestamp": "2026-01-29T00:55:32.244Z",
    "date": "2026-01-29"
  },
  {
    "userCode": "8091768",
    "action": "menu_click",
    "menu": "통합인수가이드",
    "timestamp": "2026-01-29T00:56:34.687Z",
    "date": "2026-01-29"
  },
  {
    "userCode": "1300091",
    "action": "menu_click",
    "menu": "통합인수가이드",
    "timestamp": "2026-01-29T01:00:41.440Z",
    "date": "2026-01-29"
  },
  {
    "userCode": "1300026",
    "action": "menu_click",
    "menu": "통합인수가이드",
    "timestamp": "2026-01-29T01:02:35.097Z",
    "date": "2026-01-29"
  },
  {
    "userCode": "1303072",
    "action": "menu_click",
    "menu": "수술비검색",
    "timestamp": "2026-01-29T01:05:41.652Z",
    "date": "2026-01-29"
  },
  {
    "userCode": "1303072",
    "action": "search",
    "menu": "수술비검색:티눈",
    "timestamp": "2026-01-29T01:05:44.850Z",
    "date": "2026-01-29"
  },
  {
    "userCode": "1303072",
    "action": "search",
    "menu": "수술비검색:티눈제거",
    "timestamp": "2026-01-29T01:05:48.467Z",
    "date": "2026-01-29"
  },
  {
    "userCode": "1303072",
    "action": "search",
    "menu": "수술비검색:사마귀",
    "timestamp": "2026-01-29T01:05:53.383Z",
    "date": "2026-01-29"
  },
  {
    "userCode": "1303072",
    "action": "search",
    "menu": "수술비검색:L84",
    "timestamp": "2026-01-29T01:06:09.138Z",
    "date": "2026-01-29"
  },
  {
    "userCode": "1303072",
    "action": "search",
    "menu": "수술비검색:L84",
    "timestamp": "2026-01-29T01:06:10.679Z",
    "date": "2026-01-29"
  },
  {
    "userCode": "1303072",
    "action": "search",
    "menu": "수술비검색:B07",
    "timestamp": "2026-01-29T01:06:19.094Z",
    "date": "2026-01-29"
  }
]